{
  "results":[
    {
      "q":"VW",
      "items":[

      ]
    },
    {
      "q":"SVW",
      "items":[

      ]
    },
    {
      "q":"TRK",
      "items":[
        {
          "organization":"default-organization",
          "key":"org.sonarsource.sonarqube:sonarqube",
          "name":"SonarQube",
          "highlightedText":"<em>Sonar</em>Qube"
        }
      ]
    },
    {
      "q":"BRC",
      "items":[
        {
          "organization":"default-organization",
          "key":"org.sonarsource.sonarqube:sonar-web",
          "name":"SonarQube :: Web",
          "highlightedText":"<em>Sonar</em>Qube :: Web"
        },
        {
          "organization":"default-organization",
          "key":"org.sonarsource.sonarqube:sonar-search",
          "name":"SonarQube :: Search",
          "highlightedText":"<em>Sonar</em>Qube :: Search"
        },
        {
          "organization":"default-organization",
          "key":"org.sonarsource.sonarqube:sonar-process",
          "name":"SonarQube :: Process",
          "highlightedText":"<em>Sonar</em>Qube :: Process"
        },
        {
          "organization":"default-organization",
          "key":"org.sonarsource.sonarqube:sonar-check-api",
          "name":"SonarQube :: Check API",
          "highlightedText":"<em>Sonar</em>Qube :: Check API"
        },
        {
          "organization":"default-organization",
          "key":"org.sonarsource.sonarqube:sonar-core",
          "name":"SonarQube :: Core",
          "highlightedText":"<em>Sonar</em>Qube :: Core"
        },
        {
          "organization":"default-organization",
          "key":"org.sonarsource.sonarqube:sonar-server",
          "name":"SonarQube :: Server",
          "highlightedText":"<em>Sonar</em>Qube :: Server"
        }
      ]
    },
    {
      "q":"FIL",
      "items":[
        {
          "organization":"default-organization",
          "key":"org.sonarsource.sonarqube:sonar-plugin-api:src/main/java/org/sonar/api/utils/SonarException.java",
          "name":"src/main/java/org/sonar/api/utils/SonarException.java",
          "highlightedText":"<em>Sonar</em>Exception.java"
        },
        {
          "organization":"default-organization",
          "key":"org.sonarsource.sonarqube:sonar-plugin-api:src/main/java/org/sonarsource/api/sonarlint/SonarLintSide.java",
          "name":"src/main/java/org/sonarsource/api/sonarlint/SonarLintSide.java",
          "highlightedText":"<em>Sonar</em>LintSide.java"
        }
      ]
    },
    {
      "q":"UTS",
      "items":[
        {
          "organization":"default-organization",
          "key":"org.sonarsource.sonarqube:sonar-plugin-api:src/test/java/org/sonar/api/SonarQubeVersionTest.java",
          "name":"src/test/java/org/sonar/api/SonarQubeVersionTest.java",
          "highlightedText":"<em>Sonar</em>QubeVersionTest.java"
        }
      ]
    }
  ]
}
